pipeline_processor.v
`timescale 1ns / 1ps

module pipeline_processor (
    input clk,
    input reset
);
    // Instruction opcodes
    localparam ADD  = 4'b0001;
    localparam SUB  = 4'b0010;
    localparam LOAD = 4'b0011;

    // Registers
    reg [15:0] instruction_mem [0:15];
    reg [7:0] register_file [0:15];

    // Pipeline registers
    reg [15:0] IF_ID;
    reg [15:0] ID_EX;
    reg [7:0]  EX_WB_result;
    reg [3:0]  EX_WB_dest;

    // Instruction Fetch
    reg [3:0] PC;
    wire [15:0] instruction = instruction_mem[PC];

    // Decode
    wire [3:0] opcode = IF_ID[15:12];
    wire [3:0] rd     = IF_ID[11:8];
    wire [3:0] rs1    = IF_ID[7:4];
    wire [3:0] rs2    = IF_ID[3:0];
    wire [7:0] reg_data1 = register_file[rs1];
    wire [7:0] reg_data2 = register_file[rs2];

    // Execute
    reg [7:0] alu_result;

    // Writeback
    always @(posedge clk) begin
        if (reset) begin
            PC <= 0;
        end else begin
            // IF Stage
            IF_ID <= instruction;
            PC <= PC + 1;

            // ID to EX Stage
            ID_EX <= IF_ID;

            // EX Stage
            case (ID_EX[15:12])
                ADD:  alu_result <= register_file[ID_EX[7:4]] + register_file[ID_EX[3:0]];
                SUB:  alu_result <= register_file[ID_EX[7:4]] - register_file[ID_EX[3:0]];
                LOAD: alu_result <= {4'b0000, ID_EX[3:0]}; // immediate
                default: alu_result <= 8'h00;
            endcase

            EX_WB_result <= alu_result;
            EX_WB_dest   <= ID_EX[11:8];

            // WB Stage
            register_file[EX_WB_dest] <= EX_WB_result;
        end
    end

    // Initialize instruction memory and registers
    integer i;
    initial begin
        // Preload instructions
        instruction_mem[0] = {ADD, 4'd1, 4'd2, 4'd3};   // R1 = R2 + R3
        instruction_mem[1] = {SUB, 4'd4, 4'd1, 4'd2};   // R4 = R1 - R2
        instruction_mem[2] = {LOAD, 4'd5, 4'd0, 4'd9};  // R5 = 9
        instruction_mem[3] = {ADD, 4'd6, 4'd5, 4'd5};   // R6 = R5 + R5

        for (i = 0; i < 16; i = i + 1) begin
            register_file[i] = i;
        end
    end

endmodule

pipeline_processor_tb.v
`timescale 1ns / 1ps

module pipeline_processor_tb;

    reg clk, reset;

    pipeline_processor uut (
        .clk(clk),
        .reset(reset)
    );

    initial begin
        $dumpfile("pipeline.vcd");
        $dumpvars(0, pipeline_processor_tb);

        clk = 0; reset = 1;
        #10 reset = 0;

        // Run for a few clock cycles
        #100 $finish;
    end

    always #5 clk = ~clk; // 10ns clock

endmodule

pipeline.vcd
$date
	Mon Jul 28 17:24:34 2025
$end
$version
	Icarus Verilog
$end
$timescale
	1ps
$end
$scope module pipeline_processor_tb $end
$var reg 1 ! clk $end
$var reg 1 " reset $end
$scope module uut $end
$var wire 1 # clk $end
$var wire 16 $ instruction [15:0] $end
$var wire 4 % opcode [3:0] $end
$var wire 4 & rd [3:0] $end
$var wire 8 ' reg_data1 [7:0] $end
$var wire 8 ( reg_data2 [7:0] $end
$var wire 1 ) reset $end
$var wire 4 * rs1 [3:0] $end
$var wire 4 + rs2 [3:0] $end
$var reg 4 , EX_WB_dest [3:0] $end
$var reg 8 - EX_WB_result [7:0] $end
$var reg 16 . ID_EX [15:0] $end
$var reg 16 / IF_ID [15:0] $end
$var reg 4 0 PC [3:0] $end
$var reg 8 1 alu_result [7:0] $end
$var integer 32 2 i [31:0] $end
$upscope $end
$upscope $end
$enddefinitions $end
#0
$dumpvars
b10000 2
bx 1
bx 0
bx /
bx .
bx -
bx ,
bx +
bx *
1)
bx (
bx '
bx &
bx %
bx $
0#
1"
0!
$end
#5000
b0 0
b1000100100011 $
1!
1#
#10000
0!
0#
0"
0)
#15000
b1 %
b1 &
b10 '
b10 *
b11 (
b11 +
b0 1
b1 0
b10010000010010 $
b1000100100011 /
1!
1#
#20000
0!
0#
#25000
b10 %
b100 &
b1 '
b1 *
b10 (
b10 +
b0 -
b1000100100011 .
b10 0
b11010100001001 $
b10010000010010 /
1!
1#
#30000
0!
0#
#35000
b11 %
b101 &
b0 '
b0 *
b1001 (
b1001 +
b1 ,
b101 1
b10010000010010 .
b11 0
b1011001010101 $
b11010100001001 /
1!
1#
#40000
0!
0#
#45000
b1 %
b110 &
b101 '
b101 *
b101 (
b101 +
b100 ,
b101 -
b11111111 1
b11010100001001 .
b100 0
bx $
b1011001010101 /
1!
1#
#50000
0!
0#
#55000
bx %
bx &
bx '
bx *
bx (
bx +
b101 ,
b11111111 -
b1001 1
b1011001010101 .
b101 0
bx /
1!
1#
#60000
0!
0#
#65000
b110 ,
b1001 -
b1010 1
bx .
b110 0
1!
1#
#70000
0!
0#
#75000
bx ,
b1010 -
b0 1
b111 0
1!
1#
#80000
0!
0#
#85000
b0 -
b1000 0
1!
1#
#90000
0!
0#
#95000
b1001 0
1!
1#
#100000
0!
0#
#105000
b1010 0
1!
1#
